{
    "Willing Submission": false,
    "Twisted Laboratory": false,
    "Altar of Torment": false,
    "Abomination Workshop": false,
    "Archon's Palace": false,
    "Holding Cell": false,
    "Crucible of Malediction": false,
    "Raiding Portal": false,
    "Hunting Grounds": false,
    "Klaivex Warleader (Errata)": false,
    "Gut and Pillage (Errata)": false,
    "Syren Zythlex (Errata)": false,
    "Kabalite Blackguard (Errata)": false,
    "Murder of Razorwings": false,
    "Mandrake Fearmonger": false,
    "Pain Crafter": false,
    "Corrupted Clawed Fiend": false,
    "Supplicant of Pain": false,
    "Black Heart Ravager": false,
    "Sybarite Marksman": false,
    "Beastmaster Harvester": false,
    "Coliseum Fighters": false,
    "Haemonculus Tormentor": false,
    "Mandrake Cutthroat": false,
    "Kabalite Harriers": false,
    "Mindless Pain Addict": false,
    "Vile Raider": false,
    "Stalking Ur-Ghul": false,
    "Arrogant Haemonculus": false,
    "Bloodied Reavers": false,
    "Kabalite Strike Force": false,
    "Solarite Avetys": false,
    "Distorted Talos": false,
    "Connoisseur of Terror": false,
    "Baleful Mandrake": false,
    "Kabal of the Ebon Law": false,
    "Sslyth Mercenary": false,
    "Masked Hunter": false,
    "Dark Lance Raider": false,
    "Kabalite Halfborn": false,
    "Shadowed Thorns Venom": false,
    "Syren Zythlex": false,
    "Dying Sun Marauder": false,
    "Treacherous Lhamaean": false,
    "Uber Grotesque": false,
    "Klaivex Warleader": false,
    "Beasthunter Wyches": false,
    "Raiding Kabal": false,
    "Hydrae Stalker": false,
    "Kabalite Blackguard": false,
    "Incubus Warrior": false,
    "Hellion Gang": false,
    "Flayed Skull Slaver": false,
    "Bladed Lotus Rifle": false,
    "Suffering": false,
    "Hypex Injector": false,
    "Shadowed Thorns Bodysuit": false,
    "The Shadow Suit": false,
    "Torturer's Masks": false,
    "Hallucinogen Grenade": false,
    "Electrocorrosive Whip": false,
    "Shadow Field": false,
    "Catatonic Pain": false,
    "Despise": false,
    "Run Down": false,
    "Supply Line Incursion": false,
    "Raid": false,
    "Dark Possession": false,
    "Rapid Assault": false,
    "Visions of Agony": false,
    "Searing Brand": false,
    "Soul Seizure": false,
    "Power from Pain": false,
    "Archon's Terror": false,
    "Gut and Pillage": false,
    "Slake the Thirst": false,
    "A Thousand Cuts": false,
    "Urien's Oubliette": false,
    "Ichor Gauntlet": false,
    "Rakarth's Experimentations": false,
    "Twisted Wracks": false,
    "Urien Rakarth": false,
    "Agonizer of Bren": false,
    "Pact of the Haemonculi": false,
    "Khymera Den": false,
    "Kith's Khymeramasters": false,
    "Packmaster Kith": false,
    "Reveal the Blade": false,
    "Cloak of Shade": false,
    "Shadow Hunt": false,
    "Liatha's Retinue": false,
    "Liatha": true,
    "Host of the Emissary": false,
    "Attuned Gyrinx": false,
    "Triumvirate of Ynnead": false,
    "Yvraine's Entourage": false,
    "Yvraine": true,
    "Prophets of Flesh": false,
    "The Broken Sigil": false,
    "The Flayed Mask": false,
    "Last Breath": false,
    "The Nexus of Shadows": false,
    "Inevitable Betrayal": false,
    "Shadowed Thorns Pillagers": false,
    "Archon Salaine Morn": false
}